LICENSE
MANIFEST.in
README.rst
setup.py
django_fancytree.egg-info/PKG-INFO
django_fancytree.egg-info/SOURCES.txt
django_fancytree.egg-info/dependency_links.txt
django_fancytree.egg-info/requires.txt
django_fancytree.egg-info/top_level.txt
fancytree/__init__.py
fancytree/models.py
fancytree/tests.py
fancytree/views.py
fancytree/widgets.py
fancytree/static/fancytree/jquery.fancytree-all.js
fancytree/static/fancytree/jquery.fancytree-all.min.js
fancytree/static/fancytree/jquery.fancytree.js
fancytree/static/fancytree/jquery.fancytree.min.js
fancytree/static/fancytree/skin-awesome/ui.fancytree.css
fancytree/static/fancytree/skin-awesome/ui.fancytree.min.css
fancytree/static/fancytree/skin-bootstrap/ui.fancytree.css
fancytree/static/fancytree/skin-bootstrap/ui.fancytree.min.css
fancytree/static/fancytree/skin-bootstrap-n/ui.fancytree.css
fancytree/static/fancytree/skin-bootstrap-n/ui.fancytree.min.css
fancytree/static/fancytree/skin-lion/icons.gif
fancytree/static/fancytree/skin-lion/loading.gif
fancytree/static/fancytree/skin-lion/ui.fancytree.css
fancytree/static/fancytree/skin-lion/ui.fancytree.min.css
fancytree/static/fancytree/skin-themeroller/icons.gif
fancytree/static/fancytree/skin-themeroller/loading.gif
fancytree/static/fancytree/skin-themeroller/ui.fancytree.css
fancytree/static/fancytree/skin-themeroller/ui.fancytree.min.css
fancytree/static/fancytree/skin-vista/icons.gif
fancytree/static/fancytree/skin-vista/loading.gif
fancytree/static/fancytree/skin-vista/ui.fancytree.css
fancytree/static/fancytree/skin-vista/ui.fancytree.min.css
fancytree/static/fancytree/skin-win7/icons.gif
fancytree/static/fancytree/skin-win7/loading.gif
fancytree/static/fancytree/skin-win7/ui.fancytree.css
fancytree/static/fancytree/skin-win7/ui.fancytree.min.css
fancytree/static/fancytree/skin-win8/icons.gif
fancytree/static/fancytree/skin-win8/loading.gif
fancytree/static/fancytree/skin-win8/ui.fancytree.css
fancytree/static/fancytree/skin-win8/ui.fancytree.min.css
fancytree/static/fancytree/skin-win8-n/icons.gif
fancytree/static/fancytree/skin-win8-n/loading.gif
fancytree/static/fancytree/skin-win8-n/ui.fancytree.css
fancytree/static/fancytree/skin-win8-n/ui.fancytree.min.css
