Metadata-Version: 1.1
Name: django-fancytree
Version: 0.4.0
Summary: Django forms widget that uses Fancytree to display tree data
Home-page: https://github.com/xrmx/django-fancytree
Author: Riccardo Magliocchetti
Author-email: riccardo.magliocchetti@gmail.com
License: UNKNOWN
Keywords: django,fancytree,mptt,tree
Platform: UNKNOWN
Classifier: Programming Language :: Python
Classifier: Intended Audience :: Developers
Classifier: License :: OSI Approved :: BSD License
Classifier: Operating System :: OS Independent
Classifier: Environment :: Web Environment
Classifier: Framework :: Django
Classifier: Topic :: Software Development :: Libraries :: Application Frameworks
